spanish_name_genderizer/__init__.py
spanish_name_genderizer/genderizer.py
spanish_name_genderizer/data/spanish_names.csv
spanish_name_genderizer-0.1.0.dist-info/License
spanish_name_genderizer-0.1.0.dist-info/METADATA
spanish_name_genderizer-0.1.0.dist-info/WHEEL
spanish_name_genderizer-0.1.0.dist-info/top_level.txt
spanish_name_genderizer-0.1.0.dist-info/RECORD
